cbr_custom_sc_magazine/__init__.py
cbr_custom_sc_magazine/lambdas/__init__.py
cbr_custom_sc_magazine/lambdas/handler.py
cbr_custom_sc_magazine/sc_magazine/__init__.py
cbr_custom_sc_magazine/sc_magazine/content/Http_Content__Articles.py
cbr_custom_sc_magazine/sc_magazine/content/SC_Magazine_Parser.py
cbr_custom_sc_magazine/sc_magazine/content/__init__.py
cbr_custom_sc_magazine/sc_magazine/fast_api/SC_Magazine__Fast_API.py
cbr_custom_sc_magazine/sc_magazine/fast_api/__init__.py
cbr_custom_sc_magazine/sc_magazine/fast_api/routes/Routes__Info.py
cbr_custom_sc_magazine/sc_magazine/fast_api/routes/Routes__UK.py
cbr_custom_sc_magazine/sc_magazine/schema/Article.py
cbr_custom_sc_magazine/sc_magazine/schema/Articles_Page.py
cbr_custom_sc_magazine/sc_magazine/schema/Content_Item.py
cbr_custom_sc_magazine/sc_magazine/schema/Expert_Report.py
cbr_custom_sc_magazine/sc_magazine/schema/Home_Page.py
cbr_custom_sc_magazine/sc_magazine/schema/Menu_Item.py
cbr_custom_sc_magazine/sc_magazine/schema/Navigation.py
cbr_custom_sc_magazine/sc_magazine/schema/Page_Metadata.py
cbr_custom_sc_magazine/sc_magazine/schema/Site_Config.py
cbr_custom_sc_magazine/sc_magazine/schema/Social_Link.py
cbr_custom_sc_magazine/sc_magazine/schema/Speaker.py
cbr_custom_sc_magazine/sc_magazine/schema/Video.py
cbr_custom_sc_magazine/sc_magazine/schema/Video_Platform.py
cbr_custom_sc_magazine/sc_magazine/schema/Webinar.py
cbr_custom_sc_magazine/sc_magazine/schema/__init__.py
cbr_custom_sc_magazine/utils/Version.py
cbr_custom_sc_magazine/utils/__init__.py
cbr_custom_sc_magazine/version
cbr_custom_sc_magazine-1.3.0.dist-info/LICENSE
cbr_custom_sc_magazine-1.3.0.dist-info/METADATA
cbr_custom_sc_magazine-1.3.0.dist-info/WHEEL
cbr_custom_sc_magazine-1.3.0.dist-info/RECORD
